{
  "$schema": "https://raw.githubusercontent.com/googleapis/release-please/refs/heads/main/schemas/config.json",
  "bootstrap-sha": "445caa576f70e3af253fe9d0c7eb8dbd33ebead3",
  "changelog-type": "default",
  "release-type": "rust",
  "plugins": [
    "cargo-workspace"
  ],
  "packages": {
    "cli-bin": {},
    "cli-lib": {},
    ".": {
      "changelog-path": "CHANGELOG.md",
      "bump-minor-pre-major": false,
      "bump-patch-for-minor-pre-major": false,
      "draft": false,
      "prerelease": false
    }
  },
  "changelog-sections": [
    {
      "type": "feat",
      "section": "Added"
    },
    {
      "type": "feature",
      "section": "Added"
    },
    {
      "type": "fix",
      "section": "Fixed"
    },
    {
      "type": "perf",
      "section": "Changed"
    },
    {
      "type": "revert",
      "section": "Changed"
    },
    {
      "type": "refactor",
      "section": "Changed"
    },
    {
      "type": "docs",
      "section": "Other",
      "hidden": true
    },
    {
      "type": "style",
      "section": "Other",
      "hidden": true
    },
    {
      "type": "chore",
      "section": "Other",
      "hidden": true
    },
    {
      "type": "test",
      "section": "Other",
      "hidden": true
    },
    {
      "type": "build",
      "section": "Other",
      "hidden": true
    },
    {
      "type": "ci",
      "section": "Other",
      "hidden": true
    }
  ]
}
